Client/Calculator.py
Client/__init__.py
CalcMathHamza-0.0.1.dist-info/METADATA
CalcMathHamza-0.0.1.dist-info/WHEEL
CalcMathHamza-0.0.1.dist-info/license.txt
CalcMathHamza-0.0.1.dist-info/top_level.txt
CalcMathHamza-0.0.1.dist-info/RECORD
